pandoc_d2_filter.py
pandoc_d2_filter-0.1.0.dist-info/LICENSE
pandoc_d2_filter-0.1.0.dist-info/METADATA
pandoc_d2_filter-0.1.0.dist-info/WHEEL
pandoc_d2_filter-0.1.0.dist-info/entry_points.txt
pandoc_d2_filter-0.1.0.dist-info/top_level.txt
pandoc_d2_filter-0.1.0.dist-info/RECORD
